easyremote/__init__.py
easyremote/decorators.py
easyremote/cli/__init__.py
easyremote/cli/accelerator.py
easyremote/cli/config.py
easyremote/cli/easynet.py
easyremote/core/__init__.py
easyremote/core/config.py
easyremote/core/balancing/__init__.py
easyremote/core/balancing/balancers.py
easyremote/core/balancing/health_monitor.py
easyremote/core/balancing/performance_collector.py
easyremote/core/balancing/simple_balancer.py
easyremote/core/balancing/strategies.py
easyremote/core/data/__init__.py
easyremote/core/data/analysis.py
easyremote/core/data/backends.py
easyremote/core/data/config.py
easyremote/core/data/data_types.py
easyremote/core/data/serialize.py
easyremote/core/nodes/__init__.py
easyremote/core/nodes/client.py
easyremote/core/nodes/compute_node.py
easyremote/core/nodes/server.py
easyremote/core/protos/__init__.py
easyremote/core/protos/service.proto
easyremote/core/protos/service_pb2.py
easyremote/core/protos/service_pb2_grpc.py
easyremote/core/tools/__init__.py
easyremote/core/utils/__init__.py
easyremote/core/utils/async_helpers.py
easyremote/core/utils/exceptions.py
easyremote/core/utils/logger.py
easyremote-0.1.5.1.dist-info/licenses/LICENSE
easyremote-0.1.5.1.dist-info/licenses/NOTICE.md
easyremote-0.1.5.1.dist-info/METADATA
easyremote-0.1.5.1.dist-info/WHEEL
easyremote-0.1.5.1.dist-info/entry_points.txt
easyremote-0.1.5.1.dist-info/top_level.txt
easyremote-0.1.5.1.dist-info/RECORD
