Metadata-Version: 2.4
Name: easyremote
Version: 0.1.5.1
Summary: A lightweight framework for hassle-free remote computing resource sharing
Author: Silan Hu
Author-email: Silan Hu <silan.hu@u.nus.edu>
Maintainer-email: Silan Hu <silan.hu@u.nus.edu>
License: MIT
Project-URL: Homepage, https://github.com/Qingbolan/EasyRemote
Project-URL: Documentation, https://github.com/Qingbolan/EasyRemote/blob/main/README.md
Project-URL: Repository, https://github.com/Qingbolan/EasyRemote.git
Project-URL: Bug Tracker, https://github.com/Qingbolan/EasyRemote/issues
Project-URL: Changelog, https://github.com/Qingbolan/EasyRemote/releases
Project-URL: Source Code, https://github.com/Qingbolan/EasyRemote
Keywords: remote-computing,distributed-computing,gpu-sharing,cloud-computing,grpc,asyncio
Classifier: Development Status :: 4 - Beta
Classifier: Intended Audience :: Developers
Classifier: Intended Audience :: Science/Research
Classifier: Intended Audience :: Information Technology
Classifier: Intended Audience :: System Administrators
Classifier: License :: OSI Approved :: MIT License
Classifier: Programming Language :: Python :: 3
Classifier: Programming Language :: Python :: 3.7
Classifier: Programming Language :: Python :: 3.8
Classifier: Programming Language :: Python :: 3.9
Classifier: Programming Language :: Python :: 3.10
Classifier: Programming Language :: Python :: 3.11
Classifier: Programming Language :: Python :: 3.12
Classifier: Programming Language :: Python :: 3.13
Classifier: Programming Language :: Python :: 3 :: Only
Classifier: Topic :: Software Development :: Libraries :: Python Modules
Classifier: Topic :: System :: Distributed Computing
Classifier: Topic :: System :: Networking
Classifier: Topic :: Scientific/Engineering :: Artificial Intelligence
Classifier: Topic :: Internet :: WWW/HTTP :: HTTP Servers
Classifier: Topic :: Software Development :: Libraries :: Application Frameworks
Classifier: Operating System :: OS Independent
Classifier: Environment :: Web Environment
Classifier: Environment :: Console
Classifier: Framework :: AsyncIO
Classifier: Natural Language :: English
Classifier: Natural Language :: Chinese (Simplified)
Classifier: Typing :: Typed
Requires-Python: >=3.7
License-File: LICENSE
License-File: NOTICE.md
Requires-Dist: grpcio<2.0.0,>=1.51.0
Requires-Dist: grpcio-tools<2.0.0,>=1.51.0
Requires-Dist: protobuf<6.0.0,>=4.21.0
Requires-Dist: uvicorn>=0.20.0
Requires-Dist: python-multipart>=0.0.19
Requires-Dist: rich>=13.0.0
Requires-Dist: pyfiglet>=0.8.0
Requires-Dist: GPUtil
Requires-Dist: psutil>=5.8.0
Provides-Extra: dev
Requires-Dist: pytest>=7.0.0; extra == "dev"
Requires-Dist: pytest-asyncio>=0.21.0; extra == "dev"
Requires-Dist: black>=22.0.0; extra == "dev"
Requires-Dist: isort>=5.10.0; extra == "dev"
Requires-Dist: flake8>=4.0.0; extra == "dev"
Requires-Dist: mypy>=1.0.0; extra == "dev"
Requires-Dist: pre-commit>=2.17.0; extra == "dev"
Provides-Extra: test
Requires-Dist: pytest>=7.0.0; extra == "test"
Requires-Dist: pytest-asyncio>=0.21.0; extra == "test"
Requires-Dist: pytest-cov>=4.0.0; extra == "test"
Provides-Extra: docs
Requires-Dist: mkdocs>=1.4.0; extra == "docs"
Requires-Dist: mkdocs-material>=8.0.0; extra == "docs"
Requires-Dist: mkdocstrings>=0.19.0; extra == "docs"
Dynamic: author
Dynamic: license-file
